yg.lockfile-2.3-py3.6-nspkg.pth
yg/lockfile/__init__.py
yg/lockfile/py33compat.py
yg/lockfile/test/__init__.py
yg/lockfile/test/test_lockfile.py
yg.lockfile-2.3.dist-info/DESCRIPTION.rst
yg.lockfile-2.3.dist-info/METADATA
yg.lockfile-2.3.dist-info/RECORD
yg.lockfile-2.3.dist-info/WHEEL
yg.lockfile-2.3.dist-info/metadata.json
yg.lockfile-2.3.dist-info/namespace_packages.txt
yg.lockfile-2.3.dist-info/top_level.txt
