Metadata-Version: 1.2
Name: yg.lockfile
Version: 2.3
Summary: Lockfile object with timeouts and context manager
Home-page: https://github.com/yougov/yg.lockfile
Author: Jason R. Coombs
Author-email: jaraco@jaraco.com
License: UNKNOWN
Platform: UNKNOWN
Classifier: Development Status :: 5 - Production/Stable
Classifier: Intended Audience :: Developers
Classifier: License :: OSI Approved :: MIT License
Classifier: Programming Language :: Python :: 2.7
Classifier: Programming Language :: Python :: 3
Requires-Python: >=2.7
